setup.py
jupyter_kernel_gateway_bundlers.egg-info/PKG-INFO
jupyter_kernel_gateway_bundlers.egg-info/SOURCES.txt
jupyter_kernel_gateway_bundlers.egg-info/dependency_links.txt
jupyter_kernel_gateway_bundlers.egg-info/entry_points.txt
jupyter_kernel_gateway_bundlers.egg-info/requires.txt
jupyter_kernel_gateway_bundlers.egg-info/top_level.txt
kernel_gateway_bundlers/__init__.py
kernel_gateway_bundlers/_version.py
kernel_gateway_bundlers/dockerfile_download.py
kernel_gateway_bundlers/extensionapp.py